exhaustion_check/__init__.py
exhaustion_check/exhaustion_check.py
exhaustion_check/get_first_of_first.py
exhaustion_check/pretty_sort_yaml.py
exhaustion_check-0.1.4.dist-info/LICENSE.md
exhaustion_check-0.1.4.dist-info/METADATA
exhaustion_check-0.1.4.dist-info/WHEEL
exhaustion_check-0.1.4.dist-info/entry_points.txt
exhaustion_check-0.1.4.dist-info/RECORD
